README
setup.py
r2codecut/__init__.py
r2codecut/basicutils_7x.py
r2codecut/cc_base.py
r2codecut/cc_main.py
r2codecut/lfa.py
r2codecut/map_read.py
r2codecut/maxcut.py
r2codecut/modnaming.py
r2codecut/module.py
r2codecut/snap_cg.py
r2codecut.egg-info/PKG-INFO
r2codecut.egg-info/SOURCES.txt
r2codecut.egg-info/dependency_links.txt
r2codecut.egg-info/entry_points.txt
r2codecut.egg-info/requires.txt
r2codecut.egg-info/top_level.txt