Metadata-Version: 2.1
Name: r2codecut
Version: 0.1.0
Summary: Identify Object File boundaries in binary files
Home-page: https://github.com/FernandoDoming/r2codecut
Author: Fernando Domínguez
Author-email: fernando.dom.del@gmail.com
License: GNU GPL v3
Classifier: Programming Language :: Python :: 3.5
Classifier: Programming Language :: Python :: 3.6
Classifier: Programming Language :: Python :: 3.7
Classifier: Programming Language :: Python :: 3.8
Classifier: Programming Language :: Python :: 3.9
Classifier: Programming Language :: Python :: 3.10
